qbitwave/__init__.py
qbitwave/py.typed
qbitwave/qbitwave.py
qbitwave/qbitwavend.py
qbitwave-0.2.9.dist-info/licenses/LICENSE
qbitwave-0.2.9.dist-info/METADATA
qbitwave-0.2.9.dist-info/WHEEL
qbitwave-0.2.9.dist-info/top_level.txt
qbitwave-0.2.9.dist-info/RECORD
